Workbook

Sheet Master Dashboard
A1: Category Name | B1: Total Questions | C1: High Confidence Count | D1: Medium Confidence Count | E1: Low Confidence Count | F1: None/Unknown Count | G1: Readiness Score % | H1: Status
A2: Application Inventory | B2: =COUNTA('Application Inventory'!A:A)-1 | C2: =COUNTIF('Application Inventory'!G:G,"High") | D2: =COUNTIF('Application Inventory'!G:G,"Medium") | E2: =COUNTIF('Application Inventory'!G:G,"Low") | F2: =COUNTIF('Application Inventory'!G:G,"None/Unknown") | G2: =IF(B2=0,0,(C2*100 + D2*50 + E2*25)/(B2*100)*100) | H2: =IF(G2>=80,"Green",IF(G2>=60,"Yellow","Red"))
A3: Infrastructure State | B3: =COUNTA('Infrastructure State'!A:A)-1 | C3: =COUNTIF('Infrastructure State'!G:G,"High") | D3: =COUNTIF('Infrastructure State'!G:G,"Medium") | E3: =COUNTIF('Infrastructure State'!G:G,"Low") | F3: =COUNTIF('Infrastructure State'!G:G,"None/Unknown") | G3: =IF(B3=0,0,(C3*100 + D3*50 + E3*25)/(B3*100)*100) | H3: =IF(G3>=80,"Green",IF(G3>=60,"Yellow","Red"))
A4: Licensing & Compliance | B4: =COUNTA('Licensing & Compliance'!A:A)-1 | C4: =COUNTIF('Licensing & Compliance'!G:G,"High") | D4: =COUNTIF('Licensing & Compliance'!G:G,"Medium") | E4: =COUNTIF('Licensing & Compliance'!G:G,"Low") | F4: =COUNTIF('Licensing & Compliance'!G:G,"None/Unknown") | G4: =IF(B4=0,0,(C4*100 + D4*50 + E4*25)/(B4*100)*100) | H4: =IF(G4>=80,"Green",IF(G4>=60,"Yellow","Red"))
A5: Network Architecture | B5: =COUNTA('Network Architecture'!A:A)-1 | C5: =COUNTIF('Network Architecture'!G:G,"High") | D5: =COUNTIF('Network Architecture'!G:G,"Medium") | E5: =COUNTIF('Network Architecture'!G:G,"Low") | F5: =COUNTIF('Network Architecture'!G:G,"None/Unknown") | G5: =IF(B5=0,0,(C5*100 + D5*50 + E5*25)/(B5*100)*100) | H5: =IF(G5>=80,"Green",IF(G5>=60,"Yellow","Red"))
A6: Identity & Security | B6: =COUNTA('Identity & Security'!A:A)-1 | C6: =COUNTIF('Identity & Security'!G:G,"High") | D6: =COUNTIF('Identity & Security'!G:G,"Medium") | E6: =COUNTIF('Identity & Security'!G:G,"Low") | F6: =COUNTIF('Identity & Security'!G:G,"None/Unknown") | G6: =IF(B6=0,0,(C6*100 + D6*50 + E6*25)/(B6*100)*100) | H6: =IF(G6>=80,"Green",IF(G6>=60,"Yellow","Red"))
A7: Data & Storage | B7: =COUNTA('Data & Storage'!A:A)-1 | C7: =COUNTIF('Data & Storage'!G:G,"High") | D7: =COUNTIF('Data & Storage'!G:G,"Medium") | E7: =COUNTIF('Data & Storage'!G:G,"Low") | F7: =COUNTIF('Data & Storage'!G:G,"None/Unknown") | G7: =IF(B7=0,0,(C7*100 + D7*50 + E7*25)/(B7*100)*100) | H7: =IF(G7>=80,"Green",IF(G7>=60,"Yellow","Red"))
A8: Operations & Support | B8: =COUNTA('Operations & Support'!A:A)-1 | C8: =COUNTIF('Operations & Support'!G:G,"High") | D8: =COUNTIF('Operations & Support'!G:G,"Medium") | E8: =COUNTIF('Operations & Support'!G:G,"Low") | F8: =COUNTIF('Operations & Support'!G:G,"None/Unknown") | G8: =IF(B8=0,0,(C8*100 + D8*50 + E8*25)/(B8*100)*100) | H8: =IF(G8>=80,"Green",IF(G8>=60,"Yellow","Red"))
A9: Cost & Business Case | B9: =COUNTA('Cost & Business Case'!A:A)-1 | C9: =COUNTIF('Cost & Business Case'!G:G,"High") | D9: =COUNTIF('Cost & Business Case'!G:G,"Medium") | E9: =COUNTIF('Cost & Business Case'!G:G,"Low") | F9: =COUNTIF('Cost & Business Case'!G:G,"None/Unknown") | G9: =IF(B9=0,0,(C9*100 + D9*50 + E9*25)/(B9*100)*100) | H9: =IF(G9>=80,"Green",IF(G9>=60,"Yellow","Red"))
A10: Organizational Readiness | B10: =COUNTA('Organizational Readiness'!A:A)-1 | C10: =COUNTIF('Organizational Readiness'!G:G,"High") | D10: =COUNTIF('Organizational Readiness'!G:G,"Medium") | E10: =COUNTIF('Organizational Readiness'!G:G,"Low") | F10: =COUNTIF('Organizational Readiness'!G:G,"None/Unknown") | G10: =IF(B10=0,0,(C10*100 + D10*50 + E10*25)/(B10*100)*100) | H10: =IF(G10>=80,"Green",IF(G10>=60,"Yellow","Red"))

Sheet Application Inventory
A1: Question # | B1: Question Text | C1: What We're Really Asking | D1: Why This Matters | E1: Evidence Needed | F1: Red Flags | G1: Confidence Level | H1: Notes | I1: Evidence Location
A2: Q1 | B2: Do you have a complete inventory of applications to be migrated? | C2: Can you list every application, its version, and where it runs today? | D2: Azure Migrate can't inventory what you don't know exists | E2: CMDB export, application registry, ServiceNow inventory | F2: "We think we have about 50 apps" or "IT knows what's running"
A3: Q2 | B3: Do you have documented application dependencies (what talks to what)? | C3: If App A moves to Azure, do you know which 6 other apps will break? | D3: Undocumented dependencies cause post-migration outages | E3: Application dependency maps, network flow logs, discovery tool output | F3: "The devs know" or "We'll figure it out during migration"
A4: Q3 | B4: Do you know which applications have cross-datacenter dependencies? | C4: Which apps span multiple sites and will need ExpressRoute/VPN? | D4: Cross-datacenter latency becomes cross-cloud latency | E4: Network topology diagrams, traffic flow analysis | F4: "Everything just works" or "We have good bandwidth"
A5: Q4 | B5: Have you identified which applications require specific network latency (<10ms)? | C5: Which apps will break with cloud-level latency? | D5: Azure can't fix chatty protocols or distance physics | E5: Application latency requirements, SLA documentation | F5: "Our network is fast" or "Never had latency problems"
A6: Q5 | B6: Do you know which applications share infrastructure (same VM, same database)? | C6: What's the blast radius if you migrate one thing? | D6: Shared infrastructure means you can't migrate piecemeal | E6: VM inventory showing multiple apps per server, database catalogs | F6: "Each app has its own server" (narrator: they don't)
A7: Q6 | B7: Have you documented which applications are business-critical vs. nice-to-have? | C7: What's the cost of downtime for each application? | D7: Determines migration windows, rollback strategy, and budget priority | E7: Business impact analysis, RTO/RPO documentation, C-level priorities | F7: "Everything is critical" or "We can't have downtime"
A8: Q7 | B8: Do you know who owns each application (business owner + technical owner)? | C8: Who signs off on migration and who gets called at 2am? | D8: Can't migrate what you can't get approval for | E8: RACI matrix, org chart mapping to apps, on-call rotation | F8: "IT owns everything" or "The dev team handles it"
A9: Q8 | B9: Have you identified applications that haven't been updated in 5+ years? | C9: What's your technical debt and does it still run in modern environments? | D9: Ancient apps may not work in Azure or may need expensive compatibility layers | E9: Application version inventory, last patched dates, end-of-life tracking | F9: "If it works, don't touch it" or "We have legacy but it's stable"

Sheet Infrastructure State
A1: Question # | B1: Question Text | C1: What We're Really Asking | D1: Why This Matters | E1: Evidence Needed | F1: Red Flags | G1: Confidence Level | H1: Notes | I1: Evidence Location
A2: Q1 | B2: Do you have accurate VM inventory (CPU, RAM, disk, OS version)? | C2: Can you size Azure VMs without guessing? | D2: Wrong sizes = wasted money or performance problems | E2: VMware inventory, Hyper-V reports, RVTools export, Azure Migrate assessment | F2: "We have about 200 VMs" or "Standard builds for everything"
A3: Q2 | B3: Do you have actual utilization data (not just allocated resources)? | C3: Are your VMs actually using the resources assigned to them? | D3: Most VMs are 80% idle, but you'll pay for allocated size in Azure | E3: 30 days of performance metrics (CPU, RAM, disk, network) | F3: "We sized it correctly when we built it" or "Never had performance issues"
A4: Q3 | B4: Do you know which VMs have local datastores vs. shared storage? | C4: What's the storage architecture and data locality? | D4: Affects migration approach and Azure disk selection | E4: Storage architecture diagrams, datastore mapping | F4: "Everything is on the SAN" or "It's all virtual"
A5: Q4 | B5: Have you documented backup and recovery procedures for each system? | C5: How do you recover from disasters today? | D5: Azure backup strategy should match or exceed current capabilities | E5: Backup schedules, recovery runbooks, DR test results | F5: "Veeam handles it" or "We backup everything nightly"
A6: Q5 | B6: Do you know which systems have scheduled jobs, cron tasks, or automation? | C6: What breaks if the server's IP address or hostname changes? | D6: Scheduled tasks often hardcode server names or IPs | E6: Task Scheduler exports, cron tab lists, automation runbooks | F6: "Everything is documented in the runbooks" (it's not)
A7: Q6 | B7: Have you identified which systems require static IP addresses? | C7: What's hardcoded and will break in cloud DHCP? | D7: Azure networking works differently than on-prem | E7: IP address reservations, DNS records, application configs | F7: "We use DNS for everything" (but DNS points to IPs)
A8: Q7 | B8: Do you know which physical servers are end-of-life or unsupported? | C8: What hardware is about to fail and force emergency migrations? | D8: EOL hardware creates urgency but shouldn't drive timeline | E8: Hardware lifecycle tracking, vendor support agreements | F8: "Our servers are reliable" or "We replace as needed"

Sheet Licensing & Compliance
A1: Question # | B1: Question Text | C1: What We're Really Asking | D1: Why This Matters | E1: Evidence Needed | F1: Red Flags | G1: Confidence Level | H1: Notes | I1: Evidence Location
A2: Q1 | B2: Do you have an accurate inventory of all Microsoft licenses (Windows Server, SQL Server, Office)? | C2: Can you prove what you own for Azure Hybrid Benefit? | D2: AHB can cut Azure costs 40%+ but requires active Software Assurance | E2: Microsoft Volume Licensing portal export, EA agreement details | F2: "We're properly licensed" or "Procurement handles that"
A3: Q2 | B3: Do you know which licenses include Software Assurance (SA)? | C3: What qualifies for Azure Hybrid Benefit and Reserved Instances? | D3: No SA = no AHB = 40% higher Azure costs | E3: License details showing SA coverage, renewal dates | F3: "We have Enterprise Agreement" (doesn't mean SA on everything)
A4: Q3 | B4: Have you identified third-party software that requires license mobility or re-licensing? | C4: What software stops working when moved to Azure? | D4: Oracle, IBM, SAP, and others charge differently in cloud | E4: Third-party license agreements, support ticket history | F4: "Our licenses are transferable" (prove it in writing)
A5: Q4 | B5: Do you know which applications have compliance requirements (HIPAA, PCI, SOC2, FedRAMP)? | C5: What regulatory constraints limit where data can go? | D5: Determines Azure regions, encryption requirements, audit procedures | E5: Compliance audit reports, data classification policies | F5: "We're HIPAA compliant" (what specific controls exist?)
A6: Q5 | B6: Have you documented data residency requirements (where data must stay)? | C6: Can data leave the country/state/datacenter? | D6: Limits Azure region choices and may require Azure Stack | E6: Legal requirements, customer contracts, regulatory mandates | F6: "Data can go to any Azure datacenter" (verify with legal)
A7: Q6 | B7: Do you know which systems are subject to audit and what evidence you need to retain? | C7: What logging, monitoring, and retention is required? | D7: Azure monitoring costs money; compliance is non-negotiable | E7: Compliance framework requirements (PCI DSS, NIST, etc.) | F7: "We keep logs for 30 days" (but compliance requires 7 years)

Sheet Network Architecture
A1: Question # | B1: Question Text | C1: What We're Really Asking | D1: Why This Matters | E1: Evidence Needed | F1: Red Flags | G1: Confidence Level | H1: Notes | I1: Evidence Location
A2: Q1 | B2: Do you have documented network diagrams showing VLANs, subnets, and firewall rules? | C2: Can you recreate your network segmentation in Azure? | D2: Azure NSGs and subnets work differently than physical VLANs | E2: Visio diagrams, firewall configs, IP address management (IPAM) | F2: "Our network team knows the layout" or "It's in our firewall"
A3: Q2 | B3: Do you know which applications require direct internet access vs. proxy/NAT? | C3: What's your outbound internet architecture? | D3: Determines Azure NAT Gateway, Azure Firewall, or proxy requirements | E3: Firewall logs, proxy server configs, internet access policies | F3: "Everything goes through the firewall" (how? to where?)
A4: Q3 | B4: Have you identified which applications require site-to-site connectivity? | C4: What needs ExpressRoute vs. VPN vs. can be internet-only? | D4: ExpressRoute costs $5,000+/month; VPN might work fine | E4: Application connectivity requirements, latency sensitivity | F4: "We need ExpressRoute for everything" or "VPN is good enough"
A5: Q4 | B5: Do you know your current bandwidth utilization and peak traffic patterns? | C5: Will Azure bandwidth costs surprise you? | D5: Egress from Azure costs money; ingress is free | E5: 30 days of network monitoring data, peak usage reports | F5: "We have plenty of bandwidth" or "Never had issues"
A6: Q5 | B6: Have you documented which systems have firewall rules allowing them to communicate? | C6: Can you build Azure NSGs without trial-and-error? | D6: Wrong NSG rules cause outages; too-open rules fail security audits | E6: Firewall rule exports, access control lists | F6: "We'll test connectivity after migration" (expensive approach)
A7: Q6 | B7: Do you know which DNS servers and domains are in use? | C7: How does name resolution work today? | D7: Azure needs to resolve on-prem names and vice versa | E7: DNS server configs, zone files, forwarder configurations | F7: "DNS just works" or "Active Directory handles it"
A8: Q7 | B8: Have you identified applications that use non-standard ports or protocols? | C8: What breaks if you put it behind Azure Load Balancer or Application Gateway? | D8: Azure networking has protocol and port limitations | E8: Application network requirements, firewall rules by port/protocol | F8: "Everything is HTTP/HTTPS" (is it really?)

Sheet Identity & Security
A1: Question # | B1: Question Text | C1: What We're Really Asking | D1: Why This Matters | E1: Evidence Needed | F1: Red Flags | G1: Confidence Level | H1: Notes | I1: Evidence Location
A2: Q1 | B2: Do you have documented Active Directory structure (domains, forests, trusts)? | C2: How complex is your AD environment? | D2: Determines Azure AD Connect strategy and hybrid identity approach | E2: AD topology diagrams, domain trust relationships | F2: "We have one domain" (plot twist: they have five)
A3: Q2 | B3: Do you know which applications authenticate against Active Directory? | C3: What breaks if AD connectivity goes down? | D3: Hybrid identity requires reliable AD connectivity | E3: Application authentication methods, LDAP dependencies | F3: "Everything uses AD" (what specifically?)
A4: Q3 | B4: Have you identified service accounts and their permissions? | C4: What automated processes use credentials and where? | D4: Service accounts often have hardcoded passwords or cert paths | E4: Service account inventory, permissions audit | F4: "We know all our service accounts" (you don't)
A5: Q4 | B5: Do you know which systems have local administrator accounts vs. domain-based access? | C5: How is privileged access managed? | D5: Affects Azure RBAC strategy and privileged access management | E5: Local admin audit, privileged access workstation (PAW) usage | F5: "Everyone logs in with domain accounts" (including service accounts?)
A6: Q5 | B6: Have you documented which applications require MFA and which don't? | C6: What's your authentication security baseline? | D6: Azure AD MFA is different from on-prem MFA solutions | E6: MFA policies, conditional access rules | F6: "MFA is enforced for everyone" (including service accounts? automation?)
A7: Q6 | B7: Do you know which systems generate security events and where logs are stored? | C7: How do you detect and respond to security incidents? | D7: Azure Sentinel vs. existing SIEM integration | E7: SIEM configuration, log forwarding rules, retention policies | F7: "We use [SIEM tool]" (but what data feeds into it?)

Sheet Data & Storage
A1: Question # | B1: Question Text | C1: What We're Really Asking | D1: Why This Matters | E1: Evidence Needed | F1: Red Flags | G1: Confidence Level | H1: Notes | I1: Evidence Location
A2: Q1 | B2: Do you have accurate database inventory (type, version, size, growth rate)? | C2: Can you size Azure SQL or Azure Database for [engine]? | D2: Database costs scale with size; wrong sizing is expensive | E2: Database inventory with capacity metrics, 6-month growth trend | F2: "We have SQL Server" (which version? what size?)
A3: Q2 | B3: Do you know which databases are standalone vs. clustered/replicated? | C3: What's your HA/DR architecture for databases? | D3: Determines Azure SQL options (MI, single, elastic pools, Always On) | E3: Database architecture diagrams, cluster configurations | F3: "Everything is standalone" or "We use clustering"
A4: Q3 | B4: Have you documented file share usage (size, IOPS, users, permissions)? | C4: What needs Azure Files vs. Azure NetApp Files vs. traditional SMB? | D4: Azure file share costs and performance vary wildly | E4: File server inventory, storage performance counters | F4: "We have file servers" (how many? what sizes? what performance?)
A5: Q4 | B5: Do you know which applications write to local disk vs. network storage? | C5: What storage dependencies exist? | D5: Affects Azure disk selection (Standard HDD, SSD, Premium, Ultra) | E5: Application architecture docs, disk I/O monitoring | F5: "Everything goes to the SAN" (prove it)
A6: Q5 | B6: Have you identified which data needs to be backed up and retention requirements? | C6: What's your backup policy translate to Azure Backup costs? | D6: Azure Backup charges by protected instances and retention | E6: Backup policies, retention schedules, recovery objectives | F6: "We backup everything for 30 days" (compliance says 7 years)
A7: Q6 | B7: Do you know which databases have specific backup/recovery time requirements? | C7: What's the RTO/RPO for each database? | D7: Determines backup frequency, replication strategy, costs | E7: Service level agreements, business continuity plans | F7: "We can't have downtime" (realistically, what's acceptable?)

Sheet Operations & Support
A1: Question # | B1: Question Text | C1: What We're Really Asking | D1: Why This Matters | E1: Evidence Needed | F1: Red Flags | G1: Confidence Level | H1: Notes | I1: Evidence Location
A2: Q1 | B2: Do you have documented monitoring and alerting for all critical systems? | C2: How do you know when something breaks? | D2: Azure Monitor is different from on-prem monitoring tools | E2: Monitoring tool configs, alert definitions, escalation procedures | F2: "We use [monitoring tool]" (what's monitored? who gets alerts?)
A3: Q2 | B3: Do you know which systems require scheduled maintenance windows? | C3: What can't be patched during business hours? | D3: Azure maintenance is different from on-prem patching | E3: Change calendar, maintenance schedules, blackout dates | F3: "We patch monthly" (during what window? what's the rollback plan?)
A4: Q3 | B4: Have you documented runbooks for common operational tasks? | C4: Can you operate in Azure without tribal knowledge? | D4: Azure is different; runbooks need updating | E4: Operational procedures, troubleshooting guides, escalation paths | F4: "Our team knows how to fix things" (what if they quit?)
A5: Q4 | B5: Do you know which applications require manual intervention or "someone needs to click something"? | C5: What's not actually automated? | D5: Manual processes break in cloud; need automation or Azure Functions | E5: Process documentation, task schedules, automation gaps | F5: "Everything is automated" (narrator: it's not)
A6: Q5 | B6: Have you identified which staff members support which systems? | C6: Who knows how things work and will they support Azure? | D6: Knowledge transfer takes 3-6 months; plan accordingly | E6: On-call rotations, RACI matrix, support tiers | F6: "Everyone supports everything" or "One person knows that system"
A7: Q6 | B7: Do you know which vendors provide support and what their Azure policies are? | C7: Will vendors support their apps in Azure? | D7: Some vendors refuse to support cloud deployments | E7: Vendor support agreements, cloud support policies in writing | F7: "Vendor says it's fine" (get it in writing)
A8: Q7 | B8: Have you documented incident response procedures and who to call at 2am? | C8: What happens when Azure has an outage? | D8: Azure incidents require different response than on-prem | E8: Incident response plans, escalation contacts, Azure support plan level | F8: "We have good uptime" (what's the actual incident process?)

Sheet Cost & Business Case
A1: Question # | B1: Question Text | C1: What We're Really Asking | D1: Why This Matters | E1: Evidence Needed | F1: Red Flags | G1: Confidence Level | H1: Notes | I1: Evidence Location
A2: Q1 | B2: Do you have accurate current IT costs broken down by application or service? | C2: Can you compare current costs to Azure costs? | D2: Can't prove savings if you don't know current spend | E2: IT budget breakdown, cost allocation by application | F2: "We spend $X million on IT" (but not tracked per application)
A3: Q2 | B3: Have you run Azure cost estimates using actual VM sizes and utilization? | C3: Do you know what Azure will ACTUALLY cost? | D3: Azure pricing calculators lie; need utilization-based sizing | E3: Azure Migrate assessment, Azure Pricing Calculator outputs | F3: "Azure will save us 30%" (based on what data?)
A4: Q3 | B4: Do you understand Azure cost management (tags, budgets, cost allocation)? | C4: How will you track Azure spending by department/app/team? | D4: Untracked cloud spend becomes uncontrolled cloud spend | E4: Tagging strategy, cost allocation methodology, showback/chargeback plan | F4: "We'll figure out costs later" or "Subscriptions separate costs"
A5: Q4 | B5: Have you identified which costs stay the same vs. shift to Azure? | C5: What on-prem costs remain after migration? | D5: Datacenter leases, staff, network don't disappear immediately | E5: Cost breakdown of what migrates vs. stays vs. sunsets | F5: "We'll shut down the datacenter" (when? what's the transition cost?)

Sheet Organizational Readiness
A1: Question # | B1: Question Text | C1: What We're Really Asking | D1: Why This Matters | E1: Evidence Needed | F1: Red Flags | G1: Confidence Level | H1: Notes | I1: Evidence Location
A2: Q1 | B2: Does your IT team have Azure skills or is training planned? | C2: Who actually knows Azure? | D2: Cloud requires different skills than on-prem | E2: Azure certifications, training plans, skills assessment | F2: "We'll learn as we go" or "It's just virtualization"
A3: Q2 | B3: Have you defined cloud governance policies (naming, tagging, security)? | C3: How will you prevent Azure sprawl and shadow IT? | D3: Ungoverned cloud becomes expensive and insecure fast | E3: Azure Policy definitions, naming conventions, governance framework | F3: "We'll use best practices" (which ones specifically?)
A4: Q3 | B4: Is executive leadership committed to cloud migration with budget and timeline? | C4: Is this a real initiative or a science project? | D4: Half-committed migrations fail or stall | E4: Executive sponsor identified, budget approved, timeline committed | F4: "We're exploring cloud" or "Pilot project"
A5: Q4 | B5: Have you identified who owns Azure governance, security, and cost management? | C5: Who's accountable when Azure costs 3x estimates? | D5: Shared responsibility doesn't mean nobody's responsible | E5: Organizational chart with Azure roles, RACI matrix | F5: "Cloud team handles it" (handles what specifically?)
